obsidian2html/__init__.py
obsidian2html/__main__.py
obsidian2html/cmd.py
obsidian2html/markoext.py
obsidian2html/obsidian2html.py
obsidian2html/py.typed
obsidian2html-0.1.2.dist-info/METADATA
obsidian2html-0.1.2.dist-info/WHEEL
obsidian2html-0.1.2.dist-info/entry_points.txt
obsidian2html-0.1.2.dist-info/RECORD
