Metadata-Version: 2.3
Name: obsidian2html
Version: 0.1.2
Summary: Convert Obsidian-flavoured markdown to HTML
Author-email: Dan Strong <dan@glyx.co.uk>
Requires-Python: >=3.8
Requires-Dist: marko[codehilite]>=2.1.2
